review_analysis/__init__.py
review_analysis/main.py
google_review_analysis-0.0.5.dist-info/METADATA
google_review_analysis-0.0.5.dist-info/WHEEL
google_review_analysis-0.0.5.dist-info/top_level.txt
google_review_analysis-0.0.5.dist-info/RECORD
