Metadata-Version: 2.1
Name: google_review_analysis
Version: 0.0.5
Summary: A python library for negative google review analysis.
Author: Nikolas Kapralos
Requires-Python: >=3.11
Requires-Dist: tiktoken==0.9.0
Requires-Dist: sentence-transformers==3.4.1
Requires-Dist: transformers==4.49.0
Requires-Dist: openai==1.66.3
Requires-Dist: selenium==4.29.0
Requires-Dist: matplotlib==3.10.1
